LICENSE.txt
README.md
setup.cfg
setup.py
flask_strapi/__init__.py
flask_strapi/utils.py
flask_strapi.egg-info/PKG-INFO
flask_strapi.egg-info/SOURCES.txt
flask_strapi.egg-info/dependency_links.txt
flask_strapi.egg-info/not-zip-safe
flask_strapi.egg-info/requires.txt
flask_strapi.egg-info/top_level.txt
tests/__init__.py
tests/a.py